{"_env":"NODEJS","_serializationMethod":"normal","_autosave":false,"_autosaveInterval":5000,"_collections":[{"name":"items","unindexedSortComparator":"js","defaultLokiOperatorPackage":"js","_dynamicViews":[],"uniqueNames":[],"transforms":{},"rangedIndexes":{},"_data":[{"slug":"221116_astra_install","description":"В сегодняшней статье расскажу, как установить Astra Linux на твой ПеКа. И да, я знаю, что подобных гайдов уже навалом в энтернетах, но с чего то нужно начинать писать этот бложек... Так что почитай.","title":"Еще один гайд, как установить Linux, Astra Linux","toc":[{"id":"поедемте","depth":2,"text":"Поедемте..."}],"body":{"type":"root","children":[{"type":"element","tag":"p","props":{},"children":[{"type":"text","value":"В сегодняшней статье расскажу, как установить Astra Linux на твой ПеКа.\nИ да, я знаю, что подобных гайдов уже навалом в энтернетах, но с чего то нужно начинать писать этот бложек... Так что почитай."}]},{"type":"text","value":"\n"},{"type":"element","tag":"blockquote","props":{},"children":[{"type":"text","value":"\n"},{"type":"element","tag":"p","props":{},"children":[{"type":"text","value":"Внимательным будь!"}]},{"type":"text","value":"\n"},{"type":"element","tag":"p","props":{},"children":[{"type":"text","value":"Ели ты не знаешь, как запускать комплюхтер с USB флешки - позови внука, пусть он почитает."}]},{"type":"text","value":"\n"}]},{"type":"text","value":"\n"},{"type":"element","tag":"h2","props":{"id":"поедемте"},"children":[{"type":"element","tag":"a","props":{"href":"#%D0%BF%D0%BE%D0%B5%D0%B4%D0%B5%D0%BC%D1%82%D0%B5","ariaHidden":"true","tabIndex":-1},"children":[{"type":"element","tag":"span","props":{"className":["icon","icon-link"]},"children":[]}]},{"type":"text","value":"Поедемте..."}]},{"type":"text","value":"\n"},{"type":"element","tag":"blockquote","props":{},"children":[{"type":"text","value":"\n"},{"type":"element","tag":"p","props":{},"children":[{"type":"text","value":"Почему же Astra?"}]},{"type":"text","value":"\n"},{"type":"element","tag":"p","props":{},"children":[{"type":"text","value":"В сложившейся ситуации, думаю, стоит внимательно присмотреться к отечественным сборкам операционок. И вкусно и полезно. Если будет желание (мое, естественно), напишу про установку и нормальную настройку Debian, т.к. это мой основной дистр."}]},{"type":"text","value":"\n"}]},{"type":"text","value":"\n"},{"type":"element","tag":"p","props":{},"children":[{"type":"text","value":"Скачать образ можно с официального сайта:"}]},{"type":"text","value":"\n"},{"type":"element","tag":"p","props":{},"children":[{"type":"element","tag":"a","props":{"href":"https://astralinux.ru/products/","rel":["nofollow","noopener","noreferrer"],"target":"_blank"},"children":[{"type":"text","value":"astralinux.ru"}]}]},{"type":"text","value":"\n"},{"type":"element","tag":"p","props":{},"children":[{"type":"text","value":"Имеется бесплатная версия, под названием \"Astra Linux Common Edition\"."}]},{"type":"text","value":"\n"},{"type":"element","tag":"p","props":{},"children":[{"type":"text","value":"Скачанный образ нужно зашить на USB флешку (ну или записать на двухслойный DVD, если у тебя нокия с толстой зарядкой).\nЗашивать можно чем угодно, хоть терминалом, но я буду использовать balenaEtcher, как самый простой способ. BalenaEtcher еще и кроссплатформенный, так что сможешь залить флешку со своего пожилого шиндовс.\nКачай, опять же, с официального сайта (вообще всегда все качай с официальных сайтов):\nbalenaEtcher - Flash OS images to SD cards & USB drives\nbalena.io\nВыбери нужную версию:\nbalenaEtcher - скачать\nПосле запуска balenaEtcher выбирай скачанный образ Astra, впихнутую в комп флешку и жми Flash!"}]},{"type":"text","value":"\n"},{"type":"element","tag":"div","props":{"className":["nuxt-content-highlight"]},"children":[{"type":"element","tag":"pre","props":{"className":["language-text","line-numbers"]},"children":[{"type":"element","tag":"code","props":{},"children":[{"type":"text","value":"Внимательным будь!\n\nВсе, что было на флешке, будет беспощадно уничтожено!\n"}]}]}]},{"type":"text","value":"\n"},{"type":"element","tag":"p","props":{},"children":[{"type":"text","value":"balenaEtcher - загрузка на USB\nНу и чаво?\nФлешка готова, стартуй с нее свой копудахтер."}]},{"type":"text","value":"\n"},{"type":"element","tag":"div","props":{"className":["nuxt-content-highlight"]},"children":[{"type":"element","tag":"pre","props":{"className":["language-text","line-numbers"]},"children":[{"type":"element","tag":"code","props":{},"children":[{"type":"text","value":"Внимательным будь!\n\nВсе, что было на твердых дисках, будет беспощадно уничтожено!\nПоэтому, заранее перенеси все свои невероятно важные файлы на дискеты или перфокарты.\n\nЕсть варианты с сохранением данных на дисках, но раз ты это читаешь, то они тебе не подойдут. Только хардкор.\n"}]}]}]},{"type":"text","value":"\n"},{"type":"element","tag":"p","props":{},"children":[{"type":"text","value":"Установка по шагам:"}]},{"type":"text","value":"\n"},{"type":"element","tag":"p","props":{},"children":[{"type":"text","value":"Astra Linux - boot"}]},{"type":"text","value":"\n"},{"type":"element","tag":"div","props":{"className":["nuxt-content-highlight"]},"children":[{"type":"element","tag":"pre","props":{"className":["language-text","line-numbers"]},"children":[{"type":"element","tag":"code","props":{},"children":[{"type":"text","value":"Внимательным будь!\n\nВот до этого момента (скрин ниже) твоя старушка виндовс еще не уничтожена. Есть шанс одуматься...\nКак только ты нажмешь \"Записать изменения на диск\" - ты запишешь изменения на диск. Кто бы мог подумать...\n"}]}]}]},{"type":"text","value":"\n"},{"type":"element","tag":"p","props":{},"children":[{"type":"text","value":"Astra Linux - Записать изменения на диск\nТеперь долго ли, коротко ли... ...жди...\nAstra Linux - Установка базовой системы\nОго, что то происходит!\nAstra Linux - выбор ядра\nЭто выбор ядра Linux. Если ты понял из этого объяснения только слово \"Это\", оставь выбранное ядро по умолчанию и просто жми \"Продолжить\".\nУстановщик астры пока сыроват, и, иногда могут возникать вот такие ошибки:\nAstra Linux - ошибка установки\nНе паникуй. Просто ставь все заново 😬\nА точнее, возвращайся на разметку дисков и форматируй базовый раздел. Очень удобно.\nНу наконец то!\nДальше всякие настройки после установки (если не знаешь, что все это значит, оставляй как есть):\nAstra Linux - выбор ПО"}]}]},"text":"\nВ сегодняшней статье расскажу, как установить Astra Linux на твой ПеКа.\nИ да, я знаю, что подобных гайдов уже навалом в энтернетах, но с чего то нужно начинать писать этот бложек... Так что почитай.\n\n> Внимательным будь!\n>\n> Ели ты не знаешь, как запускать комплюхтер с USB флешки - позови внука, пусть он почитает.\n\n## Поедемте...\n\n> Почему же Astra?\n>\n> В сложившейся ситуации, думаю, стоит внимательно присмотреться к отечественным сборкам операционок. И вкусно и полезно. Если будет желание (мое, естественно), напишу про установку и нормальную настройку Debian, т.к. это мой основной дистр.\n\nСкачать образ можно с официального сайта:\n\n[astralinux.ru](https://astralinux.ru/products/)\n\nИмеется бесплатная версия, под названием \"Astra Linux Common Edition\".\n\nСкачанный образ нужно зашить на USB флешку (ну или записать на двухслойный DVD, если у тебя нокия с толстой зарядкой).\nЗашивать можно чем угодно, хоть терминалом, но я буду использовать balenaEtcher, как самый простой способ. BalenaEtcher еще и кроссплатформенный, так что сможешь залить флешку со своего пожилого шиндовс.\nКачай, опять же, с официального сайта (вообще всегда все качай с официальных сайтов):\nbalenaEtcher - Flash OS images to SD cards & USB drives\nbalena.io\nВыбери нужную версию:\nbalenaEtcher - скачать\nПосле запуска balenaEtcher выбирай скачанный образ Astra, впихнутую в комп флешку и жми Flash!\n\n    Внимательным будь!\n\n    Все, что было на флешке, будет беспощадно уничтожено!\n\nbalenaEtcher - загрузка на USB\nНу и чаво?\nФлешка готова, стартуй с нее свой копудахтер.\n\n    Внимательным будь!\n\n    Все, что было на твердых дисках, будет беспощадно уничтожено!\n    Поэтому, заранее перенеси все свои невероятно важные файлы на дискеты или перфокарты.\n\n    Есть варианты с сохранением данных на дисках, но раз ты это читаешь, то они тебе не подойдут. Только хардкор.\n\nУстановка по шагам:\n\nAstra Linux - boot\n\n    Внимательным будь!\n\n    Вот до этого момента (скрин ниже) твоя старушка виндовс еще не уничтожена. Есть шанс одуматься...\n    Как только ты нажмешь \"Записать изменения на диск\" - ты запишешь изменения на диск. Кто бы мог подумать...\n\nAstra Linux - Записать изменения на диск\nТеперь долго ли, коротко ли... ...жди...\nAstra Linux - Установка базовой системы\nОго, что то происходит!\nAstra Linux - выбор ядра\nЭто выбор ядра Linux. Если ты понял из этого объяснения только слово \"Это\", оставь выбранное ядро по умолчанию и просто жми \"Продолжить\".\nУстановщик астры пока сыроват, и, иногда могут возникать вот такие ошибки:\nAstra Linux - ошибка установки\nНе паникуй. Просто ставь все заново 😬\nА точнее, возвращайся на разметку дисков и форматируй базовый раздел. Очень удобно.\nНу наконец то!\nДальше всякие настройки после установки (если не знаешь, что все это значит, оставляй как есть):\nAstra Linux - выбор ПО\n","dir":"/articles","path":"/articles/221116_astra_install","extension":".md","createdAt":"2022-11-16T12:16:25.262Z","updatedAt":"2022-11-16T13:31:30.801Z","meta":{"version":0,"revision":0,"created":1668606329003},"$loki":1}],"idIndex":[1],"maxId":1,"_dirty":true,"_nestedProperties":[],"transactional":false,"asyncListeners":false,"disableMeta":false,"disableChangesApi":true,"disableDeltaChangesApi":true,"cloneObjects":false,"cloneMethod":"deep","changes":[],"_fullTextSearch":{"ii":{"title":{"_store":true,"_optimizeChanges":true,"docCount":1,"docStore":[[0,{"fieldLength":8}]],"totalFieldLength":8,"root":{"k":[1077,1086,1075,1082,1091,108,97],"v":[{"k":[1097],"v":[{"k":[1077],"v":[{"d":{"df":1,"dc":[[0,1]]}}]}]},{"k":[1076],"v":[{"k":[1080],"v":[{"k":[1085],"v":[{"d":{"df":1,"dc":[[0,1]]}}]}]}]},{"k":[1072],"v":[{"k":[1081],"v":[{"k":[1076],"v":[{"k":[44],"v":[{"d":{"df":1,"dc":[[0,1]]}}]}]}]}]},{"k":[1072],"v":[{"k":[1082],"v":[{"d":{"df":1,"dc":[[0,1]]}}]}]},{"k":[1089],"v":[{"k":[1090],"v":[{"k":[1072],"v":[{"k":[1085],"v":[{"k":[1086],"v":[{"k":[1074],"v":[{"k":[1080],"v":[{"k":[1090],"v":[{"k":[1100],"v":[{"d":{"df":1,"dc":[[0,1]]}}]}]}]}]}]}]}]}]}]},{"k":[105],"v":[{"k":[110],"v":[{"k":[117],"v":[{"k":[120],"v":[{"d":{"df":1,"dc":[[0,1]]},"k":[44],"v":[{"d":{"df":1,"dc":[[0,1]]}}]}]}]}]}]},{"k":[115],"v":[{"k":[116],"v":[{"k":[114],"v":[{"k":[97],"v":[{"d":{"df":1,"dc":[[0,1]]}}]}]}]}]}]}},"description":{"_store":true,"_optimizeChanges":true,"docCount":1,"docStore":[[0,{"fieldLength":34}]],"totalFieldLength":34,"root":{"k":[1074,1089,1088,1082,1091,97,108,1085,1090,1087,1080,1076,1103,1079,1095,1075,1101,1073],"v":[{"d":{"df":1,"dc":[[0,2]]}},{"d":{"df":1,"dc":[[0,1]]},"k":[1077,1090],"v":[{"k":[1075],"v":[{"k":[1086],"v":[{"k":[1076],"v":[{"k":[1085],"v":[{"k":[1103],"v":[{"k":[1096],"v":[{"k":[1085],"v":[{"k":[1077],"v":[{"k":[1081],"v":[{"d":{"df":1,"dc":[[0,1]]}}]}]}]}]}]}]}]}]}]},{"k":[1072],"v":[{"k":[1090],"v":[{"k":[1100],"v":[{"k":[1077],"v":[{"d":{"df":1,"dc":[[0,1]]}}]}]}]}]}]},{"k":[1072],"v":[{"k":[1089],"v":[{"k":[1089],"v":[{"k":[1082],"v":[{"k":[1072],"v":[{"k":[1078],"v":[{"k":[1091],"v":[{"k":[44],"v":[{"d":{"df":1,"dc":[[0,1]]}}]}]}]}]}]}]}]}]},{"k":[1072],"v":[{"k":[1082],"v":[{"d":{"df":1,"dc":[[0,1]]}}]}]},{"k":[1089,1078],"v":[{"k":[1090],"v":[{"k":[1072],"v":[{"k":[1085],"v":[{"k":[1086],"v":[{"k":[1074],"v":[{"k":[1080],"v":[{"k":[1090],"v":[{"k":[1100],"v":[{"d":{"df":1,"dc":[[0,1]]}}]}]}]}]}]}]}]}]},{"k":[1077],"v":[{"d":{"df":1,"dc":[[0,1]]}}]}]},{"k":[115],"v":[{"k":[116],"v":[{"k":[114],"v":[{"k":[97],"v":[{"d":{"df":1,"dc":[[0,1]]}}]}]}]}]},{"k":[105],"v":[{"k":[110],"v":[{"k":[117],"v":[{"k":[120],"v":[{"d":{"df":1,"dc":[[0,1]]}}]}]}]}]},{"k":[1072,1086,1091],"v":[{"d":{"df":1,"dc":[[0,1]]},"k":[1074,1095],"v":[{"k":[1072],"v":[{"k":[1083],"v":[{"k":[1086],"v":[{"k":[1084],"v":[{"d":{"df":1,"dc":[[0,1]]}}]}]}]}]},{"k":[1080],"v":[{"k":[1085],"v":[{"k":[1072],"v":[{"k":[1090],"v":[{"k":[1100],"v":[{"d":{"df":1,"dc":[[0,1]]}}]}]}]}]}]}]},{"d":{"df":1,"dc":[[0,1]]}},{"k":[1078],"v":[{"k":[1085],"v":[{"k":[1086],"v":[{"d":{"df":1,"dc":[[0,1]]}}]}]}]}]},{"k":[1074,1086,1072],"v":[{"k":[1086],"v":[{"k":[1081],"v":[{"d":{"df":1,"dc":[[0,1]]}}]}]},{"d":{"df":1,"dc":[[0,1]]}},{"k":[1082],"v":[{"d":{"df":1,"dc":[[0,1]]}}]}]},{"k":[1077,1086,1080],"v":[{"k":[1082],"v":[{"k":[1072],"v":[{"k":[46],"v":[{"d":{"df":1,"dc":[[0,1]]}}]}]}]},{"k":[1076,1095],"v":[{"k":[1086],"v":[{"k":[1073],"v":[{"k":[1085],"v":[{"k":[1099],"v":[{"k":[1093],"v":[{"d":{"df":1,"dc":[[0,1]]}}]}]}]}]}]},{"k":[1080],"v":[{"k":[1090],"v":[{"k":[1072],"v":[{"k":[1081],"v":[{"k":[46],"v":[{"d":{"df":1,"dc":[[0,1]]}}]}]}]}]}]}]},{"k":[1089],"v":[{"k":[1072],"v":[{"k":[1090],"v":[{"k":[1100],"v":[{"d":{"df":1,"dc":[[0,1]]}}]}]}]}]}]},{"d":{"df":1,"dc":[[0,1]]}},{"k":[1072],"v":[{"k":[44],"v":[{"d":{"df":1,"dc":[[0,1]]}}]}]},{"d":{"df":1,"dc":[[0,1]]}},{"k":[1085],"v":[{"k":[1072],"v":[{"k":[1102],"v":[{"k":[44],"v":[{"d":{"df":1,"dc":[[0,1]]}}]}]}]}]},{"k":[1090,1077],"v":[{"k":[1086],"v":[{"d":{"df":1,"dc":[[0,2]]}}]},{"k":[1075],"v":[{"k":[1086],"v":[{"d":{"df":1,"dc":[[0,1]]}}]}]}]},{"k":[1072],"v":[{"k":[1081],"v":[{"k":[1076],"v":[{"k":[1086],"v":[{"k":[1074],"v":[{"d":{"df":1,"dc":[[0,1]]}}]}]}]}]}]},{"k":[1085,1090],"v":[{"k":[1090],"v":[{"k":[1077],"v":[{"k":[1088],"v":[{"k":[1085],"v":[{"k":[1077],"v":[{"k":[1090],"v":[{"k":[1072],"v":[{"k":[1093],"v":[{"k":[44],"v":[{"d":{"df":1,"dc":[[0,1]]}}]}]}]}]}]}]}]}]}]},{"k":[1086],"v":[{"k":[1090],"v":[{"d":{"df":1,"dc":[[0,1]]}}]}]}]},{"k":[1083],"v":[{"k":[1086],"v":[{"k":[1078],"v":[{"k":[1077],"v":[{"k":[1082],"v":[{"k":[46],"v":[{"k":[46],"v":[{"k":[46],"v":[{"d":{"df":1,"dc":[[0,1]]}}]}]}]}]}]}]}]}]}]}},"slug":{"_store":true,"_optimizeChanges":true,"docCount":1,"docStore":[[0,{"fieldLength":1}]],"totalFieldLength":1,"root":{"k":[50],"v":[{"k":[50],"v":[{"k":[49],"v":[{"k":[49],"v":[{"k":[49],"v":[{"k":[54],"v":[{"k":[95],"v":[{"k":[97],"v":[{"k":[115],"v":[{"k":[116],"v":[{"k":[114],"v":[{"k":[97],"v":[{"k":[95],"v":[{"k":[105],"v":[{"k":[110],"v":[{"k":[115],"v":[{"k":[116],"v":[{"k":[97],"v":[{"k":[108],"v":[{"k":[108],"v":[{"d":{"df":1,"dc":[[0,1]]}}]}]}]}]}]}]}]}]}]}]}]}]}]}]}]}]}]}]}]}]}},"text":{"_store":true,"_optimizeChanges":true,"docCount":1,"docStore":[[0,{"fieldLength":421}]],"totalFieldLength":421,"root":{"k":[1074,1089,1088,1082,1091,97,108,1085,1090,1087,1080,1076,1103,1079,1095,1075,1101,1073,62,1077,117,1092,45,1086,35,1078,40,100,1084,91,34,99,101,1093,98,1096,102,111,105,116,115,38,1083,46,1072,128556],"v":[{"d":{"df":1,"dc":[[0,4]]},"k":[1085,1082,1077,1089,1099,1087,1072,1086,1080],"v":[{"k":[1080,1091],"v":[{"k":[1084],"v":[{"k":[1072],"v":[{"k":[1090],"v":[{"k":[1077],"v":[{"k":[1083],"v":[{"k":[1100],"v":[{"k":[1085],"v":[{"k":[1099,1086],"v":[{"k":[1084],"v":[{"d":{"df":1,"dc":[[0,4]]}}]},{"d":{"df":1,"dc":[[0,1]]}}]}]}]}]}]}]}]}]},{"k":[1082],"v":[{"k":[1072],"v":[{"k":[44],"v":[{"d":{"df":1,"dc":[[0,1]]}}]}]}]}]},{"k":[1091],"v":[{"k":[1089],"v":[{"k":[1085],"v":[{"k":[1086],"v":[{"d":{"df":1,"dc":[[0,1]]}}]}]}]}]},{"k":[1088],"v":[{"k":[1089],"v":[{"k":[1080],"v":[{"k":[1103,1102],"v":[{"k":[44],"v":[{"d":{"df":1,"dc":[[0,1]]}}]},{"k":[58],"v":[{"d":{"df":1,"dc":[[0,1]]}}]}]}]}]}]},{"k":[1077,1103],"v":[{"d":{"df":1,"dc":[[0,4]]},"k":[1075,44],"v":[{"k":[1076],"v":[{"k":[1072],"v":[{"d":{"df":1,"dc":[[0,1]]}}]}]},{"d":{"df":1,"dc":[[0,2]]}}]},{"k":[1082],"v":[{"k":[1080],"v":[{"k":[1077],"v":[{"d":{"df":1,"dc":[[0,1]]}}]}]}]}]},{"k":[1073],"v":[{"k":[1077,1080,1086,1088],"v":[{"k":[1088],"v":[{"k":[1080],"v":[{"d":{"df":1,"dc":[[0,1]]}}]}]},{"k":[1088],"v":[{"k":[1072],"v":[{"k":[1081],"v":[{"d":{"df":1,"dc":[[0,1]]}}]}]}]},{"k":[1088],"v":[{"d":{"df":1,"dc":[[0,3]]}}]},{"k":[1072],"v":[{"k":[1085],"v":[{"k":[1085],"v":[{"k":[1086],"v":[{"k":[1077],"v":[{"d":{"df":1,"dc":[[0,1]]}}]}]}]}]}]}]}]},{"k":[1080],"v":[{"k":[1093],"v":[{"k":[1085],"v":[{"k":[1091],"v":[{"k":[1090],"v":[{"k":[1091],"v":[{"k":[1102],"v":[{"d":{"df":1,"dc":[[0,1]]}}]}]}]}]}]}]}]},{"k":[1078,1088],"v":[{"k":[1085],"v":[{"k":[1099],"v":[{"k":[1077],"v":[{"d":{"df":1,"dc":[[0,1]]}}]}]}]},{"k":[1080],"v":[{"k":[1072],"v":[{"k":[1085],"v":[{"k":[1090],"v":[{"k":[1099],"v":[{"d":{"df":1,"dc":[[0,1]]}}]}]}]}]}]}]},{"k":[1090,1079],"v":[{"d":{"df":1,"dc":[[0,2]]}},{"k":[1085,1074],"v":[{"k":[1080],"v":[{"k":[1082],"v":[{"k":[1072],"v":[{"k":[1090],"v":[{"k":[1100],"v":[{"d":{"df":1,"dc":[[0,1]]}}]}]}]}]}]},{"k":[1088],"v":[{"k":[1072],"v":[{"k":[1097],"v":[{"k":[1072],"v":[{"k":[1081],"v":[{"k":[1089],"v":[{"k":[1103],"v":[{"d":{"df":1,"dc":[[0,1]]}}]}]}]}]}]}]}]}]}]},{"k":[1085],"v":[{"k":[1076],"v":[{"k":[1086],"v":[{"k":[1074],"v":[{"k":[1089],"v":[{"d":{"df":1,"dc":[[0,1]]}}]}]}]}]}]}]},{"d":{"df":1,"dc":[[0,8]]},"k":[1077,1090,1083,1080,1073,1082,1072,1087,1084,1086,1074,1099],"v":[{"k":[1075],"v":[{"k":[1086],"v":[{"k":[1076],"v":[{"k":[1085],"v":[{"k":[1103],"v":[{"k":[1096],"v":[{"k":[1085],"v":[{"k":[1077],"v":[{"k":[1081],"v":[{"d":{"df":1,"dc":[[0,1]]}}]}]}]}]}]}]}]}]}]},{"k":[1072,1086],"v":[{"k":[1090,1088,1074],"v":[{"k":[1100],"v":[{"k":[1077],"v":[{"d":{"df":1,"dc":[[0,1]]}}]}]},{"k":[1090,1091],"v":[{"k":[1091],"v":[{"k":[1081],"v":[{"d":{"df":1,"dc":[[0,1]]}}]}]},{"k":[1096],"v":[{"k":[1082],"v":[{"k":[1072],"v":[{"d":{"df":1,"dc":[[0,1]]}}]}]}]}]},{"k":[1100],"v":[{"d":{"df":1,"dc":[[0,1]]}}]}]},{"k":[1080],"v":[{"k":[1090],"v":[{"d":{"df":1,"dc":[[0,1]]}}]}]}]},{"k":[1086],"v":[{"k":[1078,1074],"v":[{"k":[1080],"v":[{"k":[1074],"v":[{"k":[1096],"v":[{"k":[1077],"v":[{"k":[1081],"v":[{"k":[1089],"v":[{"k":[1103],"v":[{"d":{"df":1,"dc":[[0,1]]}}]}]}]}]}]}]}]},{"k":[1086],"v":[{"d":{"df":1,"dc":[[0,1]]}}]}]}]},{"k":[1090,1089],"v":[{"k":[1091],"v":[{"k":[1072],"v":[{"k":[1094],"v":[{"k":[1080],"v":[{"k":[1080],"v":[{"k":[44],"v":[{"d":{"df":1,"dc":[[0,1]]}}]}]}]}]}]}]},{"k":[1090],"v":[{"k":[1077],"v":[{"k":[1084],"v":[{"k":[1099],"v":[{"d":{"df":1,"dc":[[0,1]]}}]}]}]}]}]},{"k":[1086],"v":[{"k":[1088],"v":[{"k":[1082],"v":[{"k":[1072],"v":[{"k":[1084],"v":[{"d":{"df":1,"dc":[[0,1]]}}]}]}]}]}]},{"k":[1072],"v":[{"k":[1095],"v":[{"k":[1072],"v":[{"k":[1090,1085],"v":[{"k":[1100],"v":[{"d":{"df":1,"dc":[[0,2]]}}]},{"k":[1085],"v":[{"k":[1099],"v":[{"k":[1081],"v":[{"d":{"df":1,"dc":[[0,2]]}}]}]}]}]}]}]}]},{"k":[1081,1084],"v":[{"k":[1090],"v":[{"k":[1072,1086],"v":[{"d":{"df":1,"dc":[[0,1]]},"k":[58],"v":[{"d":{"df":1,"dc":[[0,1]]}}]},{"k":[1074],"v":[{"k":[41],"v":[{"k":[58],"v":[{"d":{"df":1,"dc":[[0,1]]}}]}]}]}]}]},{"k":[1099],"v":[{"k":[1081],"v":[{"d":{"df":1,"dc":[[0,1]]}}]}]}]},{"k":[1086],"v":[{"k":[1089],"v":[{"k":[1086],"v":[{"k":[1073],"v":[{"k":[46],"v":[{"d":{"df":1,"dc":[[0,1]]}}]}]}]}]}]},{"k":[1086],"v":[{"k":[1078],"v":[{"k":[1077],"v":[{"k":[1096],"v":[{"k":[1100],"v":[{"d":{"df":1,"dc":[[0,1]]}}]}]}]}]}]},{"d":{"df":1,"dc":[[0,1]]},"k":[1093],"v":[{"k":[1088],"v":[{"k":[1072],"v":[{"k":[1085],"v":[{"k":[1077],"v":[{"k":[1085],"v":[{"k":[1080],"v":[{"k":[1077],"v":[{"k":[1084],"v":[{"d":{"df":1,"dc":[[0,1]]}}]}]}]}]}]}]}]}]}]},{"k":[1086],"v":[{"k":[1077,1081,1080],"v":[{"k":[1075],"v":[{"k":[1086],"v":[{"d":{"df":1,"dc":[[0,1]]}}]}]},{"d":{"df":1,"dc":[[0,1]]}},{"d":{"df":1,"dc":[[0,1]]}}]}]},{"k":[1088],"v":[{"k":[1086],"v":[{"k":[1074],"v":[{"k":[1072],"v":[{"k":[1090],"v":[{"k":[44],"v":[{"d":{"df":1,"dc":[[0,1]]}}]}]}]}]}]}]}]},{"k":[1072],"v":[{"k":[1089,1079],"v":[{"k":[1089],"v":[{"k":[1082],"v":[{"k":[1072],"v":[{"k":[1078],"v":[{"k":[1091],"v":[{"k":[44],"v":[{"d":{"df":1,"dc":[[0,1]]}}]}]}]}]}]}]},{"d":{"df":1,"dc":[[0,1]]},"k":[1084,1076],"v":[{"k":[1077],"v":[{"k":[1090],"v":[{"k":[1082],"v":[{"k":[1091],"v":[{"d":{"df":1,"dc":[[0,1]]}}]}]}]}]},{"k":[1077],"v":[{"k":[1083],"v":[{"k":[46],"v":[{"d":{"df":1,"dc":[[0,1]]}}]}]}]}]}]}]},{"d":{"df":1,"dc":[[0,1]]},"k":[1072,1086,1088,1090],"v":[{"k":[1082,1095],"v":[{"d":{"df":1,"dc":[[0,5]]}},{"k":[1072],"v":[{"k":[1081],"v":[{"d":{"df":1,"dc":[[0,1]]},"k":[44],"v":[{"d":{"df":1,"dc":[[0,1]]}}]}]}]}]},{"k":[1084,1087,1088],"v":[{"k":[1087],"v":[{"d":{"df":1,"dc":[[0,1]]},"k":[1083],"v":[{"k":[1102],"v":[{"k":[1093],"v":[{"k":[1090],"v":[{"k":[1077],"v":[{"k":[1088],"v":[{"d":{"df":1,"dc":[[0,1]]}}]}]}]}]}]}]}]},{"k":[1091],"v":[{"k":[1076],"v":[{"k":[1072],"v":[{"k":[1093],"v":[{"k":[1090],"v":[{"k":[1077],"v":[{"k":[1088],"v":[{"k":[46],"v":[{"d":{"df":1,"dc":[[0,1]]}}]}]}]}]}]}]}]}]},{"k":[1086],"v":[{"k":[1090],"v":[{"k":[1082],"v":[{"k":[1086],"v":[{"d":{"df":1,"dc":[[0,1]]}}]}]}]}]}]},{"k":[1086],"v":[{"k":[1089],"v":[{"k":[1089],"v":[{"k":[1087],"v":[{"k":[1083],"v":[{"k":[1072],"v":[{"k":[1090],"v":[{"k":[1092],"v":[{"k":[1086],"v":[{"k":[1088],"v":[{"k":[1084],"v":[{"k":[1077],"v":[{"k":[1085],"v":[{"k":[1085],"v":[{"k":[1099],"v":[{"k":[1081],"v":[{"k":[44],"v":[{"d":{"df":1,"dc":[[0,1]]}}]}]}]}]}]}]}]}]}]}]}]}]}]}]}]}]}]},{"k":[1086],"v":[{"d":{"df":1,"dc":[[0,1]]}}]}]},{"d":{"df":1,"dc":[[0,1]]},"k":[1089,1078,1075,1085,1084,1076],"v":[{"k":[1090],"v":[{"k":[1072],"v":[{"k":[1085],"v":[{"k":[1086],"v":[{"k":[1074],"v":[{"k":[1080,1082,1097],"v":[{"k":[1090],"v":[{"k":[1100],"v":[{"d":{"df":1,"dc":[[0,1]]}}]}]},{"k":[1091,1072,1080],"v":[{"d":{"df":1,"dc":[[0,1]]}},{"d":{"df":1,"dc":[[0,2]]}},{"d":{"df":1,"dc":[[0,2]]}}]},{"k":[1080],"v":[{"k":[1082],"v":[{"d":{"df":1,"dc":[[0,1]]}}]}]}]}]}]}]}]}]},{"k":[1077],"v":[{"d":{"df":1,"dc":[[0,1]]}}]},{"k":[1086],"v":[{"k":[1076],"v":[{"k":[1085],"v":[{"k":[1086],"v":[{"k":[44],"v":[{"d":{"df":1,"dc":[[0,1]]}}]}]}]}]}]},{"k":[1080],"v":[{"k":[1095],"v":[{"k":[1090],"v":[{"k":[1086],"v":[{"k":[1078],"v":[{"k":[1077],"v":[{"k":[1085],"v":[{"k":[1086,1072],"v":[{"k":[33],"v":[{"d":{"df":1,"dc":[[0,2]]}}]},{"k":[46],"v":[{"d":{"df":1,"dc":[[0,1]]}}]}]}]}]}]}]}]}]}]},{"k":[1086],"v":[{"k":[1083],"v":[{"k":[1095],"v":[{"k":[1072],"v":[{"k":[1085],"v":[{"k":[1080],"v":[{"k":[1102],"v":[{"d":{"df":1,"dc":[[0,1]]}}]}]}]}]}]}]}]},{"k":[1086],"v":[{"k":[1073],"v":[{"k":[1085],"v":[{"k":[1086],"v":[{"k":[46],"v":[{"d":{"df":1,"dc":[[0,1]]}}]}]}]}]}]}]},{"k":[115],"v":[{"k":[116],"v":[{"k":[114],"v":[{"k":[97],"v":[{"d":{"df":1,"dc":[[0,7]]},"k":[63,44],"v":[{"d":{"df":1,"dc":[[0,1]]}},{"d":{"df":1,"dc":[[0,1]]}}]}]}]}]}]},{"k":[105],"v":[{"k":[110],"v":[{"k":[117],"v":[{"k":[120],"v":[{"d":{"df":1,"dc":[[0,8]]},"k":[46],"v":[{"d":{"df":1,"dc":[[0,1]]}}]}]}]}]}]},{"k":[1072,1086,1091,1077,1080],"v":[{"d":{"df":1,"dc":[[0,12]]},"k":[1074,1095,1087,1089,1079,1078,1082],"v":[{"k":[1072],"v":[{"k":[1083],"v":[{"k":[1086],"v":[{"k":[1084],"v":[{"d":{"df":1,"dc":[[0,1]]}}]}]}]}]},{"k":[1080],"v":[{"k":[1085],"v":[{"k":[1072],"v":[{"k":[1090],"v":[{"k":[1100],"v":[{"d":{"df":1,"dc":[[0,1]]}}]}]}]}]}]},{"k":[1080],"v":[{"k":[1096],"v":[{"k":[1091],"v":[{"d":{"df":1,"dc":[[0,1]]}}]}]}]},{"k":[1090],"v":[{"k":[1088],"v":[{"k":[1086],"v":[{"k":[1081],"v":[{"k":[1082],"v":[{"k":[1091,1080],"v":[{"d":{"df":1,"dc":[[0,1]]}},{"d":{"df":1,"dc":[[0,1]]}}]}]}]}]}]}]},{"k":[1074],"v":[{"k":[1072],"v":[{"k":[1085],"v":[{"k":[1080],"v":[{"k":[1077],"v":[{"k":[1084],"v":[{"d":{"df":1,"dc":[[0,1]]}}]}]}]}]}]}]},{"k":[1084],"v":[{"k":[1077],"v":[{"k":[1096],"v":[{"k":[1100],"v":[{"d":{"df":1,"dc":[[0,1]]}}]}]}]}]},{"k":[1086],"v":[{"k":[1085],"v":[{"k":[1077],"v":[{"k":[1094],"v":[{"d":{"df":1,"dc":[[0,1]]}}]}]}]}]}]},{"d":{"df":1,"dc":[[0,3]]},"k":[1088,1082],"v":[{"k":[1084],"v":[{"k":[1072],"v":[{"k":[1083],"v":[{"k":[1100],"v":[{"k":[1085],"v":[{"k":[1091],"v":[{"k":[1102],"v":[{"d":{"df":1,"dc":[[0,1]]}}]}]}]}]}]}]}]},{"k":[1080],"v":[{"k":[1103],"v":[{"d":{"df":1,"dc":[[0,1]]}}]}]}]},{"d":{"df":1,"dc":[[0,2]]},"k":[1078],"v":[{"k":[1085],"v":[{"k":[1086,1091],"v":[{"d":{"df":1,"dc":[[0,2]]}},{"k":[1102],"v":[{"d":{"df":1,"dc":[[0,1]]}}]}]}]}]},{"d":{"df":1,"dc":[[0,5]]},"k":[1077,1074],"v":[{"d":{"df":1,"dc":[[0,1]]}},{"k":[1077],"v":[{"k":[1088],"v":[{"k":[1086],"v":[{"k":[1103],"v":[{"k":[1090],"v":[{"k":[1085],"v":[{"k":[1086],"v":[{"d":{"df":1,"dc":[[0,1]]}}]}]}]}]}]}]}]}]},{"k":[1078],"v":[{"k":[1077],"v":[{"k":[41],"v":[{"d":{"df":1,"dc":[[0,1]]}}]}]}]}]},{"k":[1074,1086,1072,1099,46,1077],"v":[{"k":[1086,1077],"v":[{"k":[1081,1103],"v":[{"d":{"df":1,"dc":[[0,1]]}},{"d":{"df":1,"dc":[[0,1]]}}]},{"k":[1088],"v":[{"k":[1076],"v":[{"k":[1099],"v":[{"k":[1093],"v":[{"d":{"df":1,"dc":[[0,1]]}}]}]}]}]}]},{"d":{"df":1,"dc":[[0,3]]},"k":[1083,1095,33],"v":[{"k":[1089,1100],"v":[{"k":[1090],"v":[{"k":[1086],"v":[{"k":[1081],"v":[{"d":{"df":1,"dc":[[0,1]]}}]}]}]},{"k":[1082],"v":[{"k":[1086],"v":[{"d":{"df":1,"dc":[[0,3]]}}]}]}]},{"k":[1085],"v":[{"k":[1077],"v":[{"k":[1077],"v":[{"k":[44],"v":[{"d":{"df":1,"dc":[[0,1]]}}]}]}]}]},{"d":{"df":1,"dc":[[0,1]]}}]},{"k":[1082],"v":[{"d":{"df":1,"dc":[[0,2]]},"k":[1080],"v":[{"k":[1077],"v":[{"d":{"df":1,"dc":[[0,1]]}}]}]}]},{"d":{"df":1,"dc":[[0,5]]}},{"k":[1082],"v":[{"k":[46],"v":[{"d":{"df":1,"dc":[[0,1]]}}]}]},{"k":[1073,1088,1087],"v":[{"k":[1103,1077],"v":[{"d":{"df":1,"dc":[[0,1]]}},{"d":{"df":1,"dc":[[0,1]]}}]},{"k":[1084],"v":[{"k":[1080],"v":[{"k":[1085],"v":[{"k":[1072],"v":[{"k":[1083],"v":[{"k":[1086],"v":[{"k":[1084],"v":[{"k":[44],"v":[{"d":{"df":1,"dc":[[0,1]]}}]}]}]}]}]}]}]}]},{"k":[1077],"v":[{"k":[1088],"v":[{"k":[1100],"v":[{"d":{"df":1,"dc":[[0,1]]}}]}]}]}]}]},{"k":[1077,1086,1080,1091,1088,1072],"v":[{"k":[1082,1088],"v":[{"k":[1072],"v":[{"k":[46],"v":[{"d":{"df":1,"dc":[[0,1]]}}]}]},{"k":[1077,1092],"v":[{"k":[1085],"v":[{"k":[1077],"v":[{"k":[1089],"v":[{"k":[1080],"v":[{"d":{"df":1,"dc":[[0,1]]}}]}]}]}]},{"k":[1086],"v":[{"k":[1082],"v":[{"k":[1072],"v":[{"k":[1088],"v":[{"k":[1090],"v":[{"k":[1099],"v":[{"k":[46],"v":[{"d":{"df":1,"dc":[[0,1]]}}]}]}]}]}]}]}]}]}]},{"d":{"df":1,"dc":[[0,3]]},"k":[1076,1095,1079,1077,1083,1078,1089,1101,1085,1082],"v":[{"d":{"df":1,"dc":[[0,1]]},"k":[1086,1091],"v":[{"k":[1073,1081],"v":[{"k":[1085],"v":[{"k":[1099],"v":[{"k":[1093],"v":[{"d":{"df":1,"dc":[[0,1]]}}]}]}]},{"k":[1076],"v":[{"k":[1091],"v":[{"k":[1090],"v":[{"k":[46],"v":[{"d":{"df":1,"dc":[[0,1]]}}]}]}]}]}]},{"k":[1084],"v":[{"k":[1072],"v":[{"k":[1090],"v":[{"k":[1100],"v":[{"k":[46],"v":[{"k":[46],"v":[{"k":[46],"v":[{"d":{"df":1,"dc":[[0,1]]}}]}]}]}]}]}]}]}]},{"k":[1080,1077],"v":[{"k":[1090],"v":[{"k":[1072],"v":[{"k":[1081,1077],"v":[{"k":[46],"v":[{"d":{"df":1,"dc":[[0,1]]}}]},{"k":[1090],"v":[{"k":[46],"v":[{"d":{"df":1,"dc":[[0,1]]}}]}]}]}]}]},{"k":[1084],"v":[{"k":[1091],"v":[{"d":{"df":1,"dc":[[0,1]]}}]}]}]},{"k":[1086],"v":[{"k":[1074],"v":[{"k":[1080],"v":[{"d":{"df":1,"dc":[[0,1]]}}]}]}]},{"k":[1076],"v":[{"k":[1077],"v":[{"k":[1084],"v":[{"k":[1090],"v":[{"k":[1077],"v":[{"k":[46],"v":[{"k":[46],"v":[{"k":[46],"v":[{"d":{"df":1,"dc":[[0,1]]}}]}]}]}]}]}]}]}]},{"k":[1077],"v":[{"k":[1079],"v":[{"k":[1085],"v":[{"k":[1086],"v":[{"k":[46],"v":[{"d":{"df":1,"dc":[[0,1]]}}]}]}]}]}]},{"k":[1080],"v":[{"k":[1083],"v":[{"k":[1086],"v":[{"k":[1075],"v":[{"k":[1086],"v":[{"d":{"df":1,"dc":[[0,1]]}}]}]}]}]}]},{"k":[1083],"v":[{"k":[1077],"v":[{"d":{"df":1,"dc":[[0,2]]}}]}]},{"k":[1090],"v":[{"k":[1086],"v":[{"k":[1084],"v":[{"k":[1091],"v":[{"k":[44],"v":[{"d":{"df":1,"dc":[[0,1]]}}]}]}]}]}]},{"k":[1103],"v":[{"k":[1083],"v":[{"d":{"df":1,"dc":[[0,1]]}}]}]},{"k":[1072],"v":[{"d":{"df":1,"dc":[[0,1]]}}]}]},{"k":[1089],"v":[{"k":[1072],"v":[{"k":[1090],"v":[{"k":[1100],"v":[{"d":{"df":1,"dc":[[0,1]]}}]}]}]}]},{"k":[1089],"v":[{"k":[1090],"v":[{"k":[1100],"v":[{"d":{"df":1,"dc":[[0,1]]}}]}]}]},{"k":[1080,1086],"v":[{"k":[1089],"v":[{"k":[1084],"v":[{"k":[1086],"v":[{"k":[1090],"v":[{"k":[1088],"v":[{"k":[1077],"v":[{"k":[1090],"v":[{"k":[1100],"v":[{"k":[1089],"v":[{"k":[1103],"v":[{"d":{"df":1,"dc":[[0,1]]}}]}]}]}]}]}]}]}]}]}]},{"d":{"df":1,"dc":[[0,1]]},"k":[1089,1080],"v":[{"k":[1090],"v":[{"k":[1086],"v":[{"d":{"df":1,"dc":[[0,2]]},"k":[1081],"v":[{"d":{"df":1,"dc":[[0,1]]}}]}]}]},{"k":[1089],"v":[{"k":[1093],"v":[{"k":[1086],"v":[{"k":[1076],"v":[{"k":[1080],"v":[{"k":[1090],"v":[{"k":[33],"v":[{"d":{"df":1,"dc":[[0,1]]}}]}]}]}]}]}]}]}]}]},{"k":[1085],"v":[{"k":[1080],"v":[{"k":[1082],"v":[{"k":[1091],"v":[{"k":[1081],"v":[{"k":[46],"v":[{"d":{"df":1,"dc":[[0,1]]}}]}]}]}]}]}]}]},{"d":{"df":1,"dc":[[0,9]]},"k":[1084,1083,1089,1079,44,1085],"v":[{"k":[1077],"v":[{"k":[1077],"v":[{"k":[1090],"v":[{"k":[1089],"v":[{"k":[1103],"v":[{"d":{"df":1,"dc":[[0,1]]}}]}]}]}]}]},{"k":[1080],"v":[{"d":{"df":1,"dc":[[0,2]]}}]},{"k":[1087],"v":[{"k":[1086],"v":[{"k":[1083],"v":[{"k":[1100],"v":[{"k":[1079],"v":[{"k":[1086],"v":[{"k":[1074],"v":[{"k":[1072],"v":[{"k":[1090],"v":[{"k":[1100],"v":[{"d":{"df":1,"dc":[[0,1]]}}]}]}]}]}]}]}]}]}]}]},{"d":{"df":1,"dc":[[0,1]]},"k":[1084],"v":[{"k":[1077],"v":[{"k":[1085],"v":[{"k":[1077],"v":[{"k":[1085],"v":[{"k":[1080],"v":[{"k":[1103],"v":[{"d":{"df":1,"dc":[[0,3]]}}]}]}]}]}]}]}]},{"d":{"df":1,"dc":[[0,1]]}},{"k":[1086],"v":[{"k":[1075],"v":[{"k":[1076],"v":[{"k":[1072],"v":[{"d":{"df":1,"dc":[[0,1]]}}]}]}]}]}]},{"k":[1072,1091,1080,1074,1086],"v":[{"k":[44,1085,1083],"v":[{"d":{"df":1,"dc":[[0,1]]}},{"k":[1085],"v":[{"k":[1099],"v":[{"k":[1093],"v":[{"d":{"df":1,"dc":[[0,1]]}}]}]}]},{"k":[1100],"v":[{"k":[1096],"v":[{"k":[1077],"v":[{"d":{"df":1,"dc":[[0,1]]}}]}]}]}]},{"k":[1084],"v":[{"k":[1072],"v":[{"k":[1102],"v":[{"k":[44],"v":[{"d":{"df":1,"dc":[[0,1]]}}]}]}]}]},{"k":[1089],"v":[{"k":[1090,1082],"v":[{"k":[1088],"v":[{"k":[46],"v":[{"d":{"df":1,"dc":[[0,1]]}}]}]},{"d":{"df":1,"dc":[[0,1]]},"k":[1072,1077,34,46,1086],"v":[{"k":[1093],"v":[{"k":[44],"v":[{"d":{"df":1,"dc":[[0,2]]}}]}]},{"k":[1090],"v":[{"k":[1099],"v":[{"d":{"df":1,"dc":[[0,1]]}}]}]},{"d":{"df":1,"dc":[[0,1]]}},{"d":{"df":1,"dc":[[0,1]]}},{"k":[1074],"v":[{"d":{"df":1,"dc":[[0,1]]}}]}]}]}]},{"k":[1091],"v":[{"k":[1093],"v":[{"k":[1089],"v":[{"k":[1083],"v":[{"k":[1086],"v":[{"k":[1081],"v":[{"k":[1085],"v":[{"k":[1099],"v":[{"k":[1081],"v":[{"d":{"df":1,"dc":[[0,1]]}}]}]}]}]}]}]}]}]}]},{"d":{"df":1,"dc":[[0,1]]},"k":[1083],"v":[{"k":[1075],"v":[{"k":[1086],"v":[{"d":{"df":1,"dc":[[0,1]]}}]}]}]}]},{"d":{"df":1,"dc":[[0,2]]},"k":[1076],"v":[{"k":[1088],"v":[{"k":[1072,1086],"v":[{"d":{"df":1,"dc":[[0,2]]}},{"d":{"df":1,"dc":[[0,1]]}}]}]}]},{"k":[1085,1072],"v":[{"k":[1072],"v":[{"k":[1102,1077,1095],"v":[{"k":[44],"v":[{"d":{"df":1,"dc":[[0,1]]}}]},{"k":[1096],"v":[{"k":[1100],"v":[{"k":[44],"v":[{"d":{"df":1,"dc":[[0,2]]}}]}]}]},{"k":[1080],"v":[{"k":[1090],"v":[{"k":[44],"v":[{"d":{"df":1,"dc":[[0,1]]}}]}]}]}]}]},{"k":[1087,1096,1088,1083,1075,1085],"v":[{"k":[1091,1080],"v":[{"k":[1089],"v":[{"k":[1082],"v":[{"k":[1072],"v":[{"d":{"df":1,"dc":[[0,1]]},"k":[1090],"v":[{"k":[1100],"v":[{"d":{"df":1,"dc":[[0,1]]}}]}]}]}]}]},{"k":[1089,1096],"v":[{"k":[1072],"v":[{"k":[1090],"v":[{"k":[1100],"v":[{"d":{"df":1,"dc":[[0,2]]}}]}]}]},{"k":[1077],"v":[{"k":[1096],"v":[{"k":[1100],"v":[{"d":{"df":1,"dc":[[0,1]]}}]}]}]}]}]},{"k":[1080],"v":[{"k":[1090,1074],"v":[{"k":[1100],"v":[{"d":{"df":1,"dc":[[0,1]]}}]},{"k":[1072],"v":[{"k":[1090],"v":[{"k":[1100],"v":[{"d":{"df":1,"dc":[[0,1]]}}]}]}]}]}]},{"k":[1103,1072],"v":[{"k":[1076],"v":[{"k":[1082],"v":[{"k":[1086],"v":[{"k":[1081],"v":[{"k":[41],"v":[{"k":[46],"v":[{"d":{"df":1,"dc":[[0,1]]}}]}]}]}]}]}]},{"k":[1085],"v":[{"k":[1077],"v":[{"k":[1077],"v":[{"d":{"df":1,"dc":[[0,1]]}}]}]}]}]},{"k":[1080],"v":[{"k":[1090],"v":[{"k":[1100],"v":[{"d":{"df":1,"dc":[[0,1]]}}]}]}]},{"k":[1088],"v":[{"k":[1091],"v":[{"k":[1079],"v":[{"k":[1082],"v":[{"k":[1072],"v":[{"d":{"df":1,"dc":[[0,1]]}}]}]}]}]}]},{"k":[1086],"v":[{"k":[1074],"v":[{"k":[1086],"v":[{"d":{"df":1,"dc":[[0,1]]}}]}]}]}]}]},{"k":[1090,1077,1072,1080],"v":[{"k":[1086],"v":[{"d":{"df":1,"dc":[[0,7]]}}]},{"k":[1075,1084],"v":[{"k":[1086],"v":[{"d":{"df":1,"dc":[[0,1]]}}]},{"d":{"df":1,"dc":[[0,1]]}}]},{"k":[1074],"v":[{"k":[1086],"v":[{"k":[63],"v":[{"d":{"df":1,"dc":[[0,1]]}}]}]}]},{"k":[1090],"v":[{"k":[1072],"v":[{"k":[1077],"v":[{"k":[1096],"v":[{"k":[1100],"v":[{"k":[44],"v":[{"d":{"df":1,"dc":[[0,1]]}}]}]}]}]}]}]}]},{"k":[1072,1086],"v":[{"k":[1081],"v":[{"k":[1076],"v":[{"k":[1086],"v":[{"k":[1074],"v":[{"d":{"df":1,"dc":[[0,1]]}}]}]}]}]},{"k":[1090],"v":[{"k":[1086],"v":[{"k":[1074],"v":[{"k":[1072],"v":[{"k":[44],"v":[{"d":{"df":1,"dc":[[0,1]]}}]}]}]}]}]}]},{"k":[1085,1090],"v":[{"k":[1090],"v":[{"k":[1077],"v":[{"k":[1088],"v":[{"k":[1085],"v":[{"k":[1077],"v":[{"k":[1090],"v":[{"k":[1072],"v":[{"k":[1093],"v":[{"k":[44],"v":[{"d":{"df":1,"dc":[[0,1]]}}]}]}]}]}]}]}]}]}]},{"k":[1086],"v":[{"d":{"df":1,"dc":[[0,4]]},"k":[1090,1075],"v":[{"d":{"df":1,"dc":[[0,1]]}},{"k":[1086],"v":[{"d":{"df":1,"dc":[[0,2]]}}]}]}]}]},{"k":[1083,1091,1077,1099,1072],"v":[{"k":[1086],"v":[{"k":[1078],"v":[{"k":[1077],"v":[{"k":[1082],"v":[{"k":[46],"v":[{"k":[46],"v":[{"k":[46],"v":[{"d":{"df":1,"dc":[[0,1]]}}]}]}]}]}]}]}]},{"k":[1076],"v":[{"k":[1100,1077,1091],"v":[{"k":[33],"v":[{"d":{"df":1,"dc":[[0,4]]}}]},{"k":[1090],"v":[{"d":{"df":1,"dc":[[0,3]]}}]},{"d":{"df":1,"dc":[[0,1]]}}]}]},{"k":[1089],"v":[{"k":[1087],"v":[{"k":[1083,1086],"v":[{"k":[1072],"v":[{"k":[1090],"v":[{"k":[1085],"v":[{"k":[1072],"v":[{"k":[1103],"v":[{"d":{"df":1,"dc":[[0,1]]}}]}]}]}]}]},{"k":[1097],"v":[{"k":[1072],"v":[{"k":[1076],"v":[{"k":[1085],"v":[{"k":[1086],"v":[{"d":{"df":1,"dc":[[0,2]]}}]}]}]}]}]}]}]}]},{"d":{"df":1,"dc":[[0,1]]},"k":[1083],"v":[{"k":[1086],"v":[{"d":{"df":1,"dc":[[0,2]]}}]}]},{"k":[1079],"v":[{"k":[1086],"v":[{"k":[1074],"v":[{"k":[1086,1099],"v":[{"k":[1081],"v":[{"d":{"df":1,"dc":[[0,1]]}}]},{"k":[1081],"v":[{"d":{"df":1,"dc":[[0,1]]}}]}]}]}]}]}]},{"d":{"df":1,"dc":[[0,6]]}},{"k":[1083,1089,1097],"v":[{"k":[1080],"v":[{"d":{"df":1,"dc":[[0,1]]}}]},{"k":[1083,1090],"v":[{"k":[1080],"v":[{"d":{"df":1,"dc":[[0,3]]}}]},{"k":[1077,1100],"v":[{"k":[1089],"v":[{"k":[1090],"v":[{"k":[1074],"v":[{"k":[1077],"v":[{"k":[1085],"v":[{"k":[1085],"v":[{"k":[1086],"v":[{"k":[41],"v":[{"k":[44],"v":[{"d":{"df":1,"dc":[[0,1]]}}]}]}]}]}]}]}]}]}]},{"d":{"df":1,"dc":[[0,2]]},"k":[41],"v":[{"k":[58],"v":[{"d":{"df":1,"dc":[[0,1]]}}]}]}]}]},{"k":[1077],"v":[{"d":{"df":1,"dc":[[0,2]]}}]}]},{"k":[115],"v":[{"k":[98],"v":[{"d":{"df":1,"dc":[[0,4]]}}]}]},{"k":[1083,1072,1086],"v":[{"k":[1077],"v":[{"k":[1096],"v":[{"k":[1082],"v":[{"k":[1080,1091,1077,1072],"v":[{"d":{"df":1,"dc":[[0,1]]}},{"d":{"df":1,"dc":[[0,3]]}},{"k":[44],"v":[{"d":{"df":1,"dc":[[0,1]]}}]},{"d":{"df":1,"dc":[[0,1]]}}]}]}]}]},{"k":[1081],"v":[{"k":[1083],"v":[{"k":[1099],"v":[{"d":{"df":1,"dc":[[0,1]]}}]}]}]},{"k":[1088],"v":[{"k":[1084],"v":[{"k":[1072],"v":[{"k":[1090],"v":[{"k":[1080],"v":[{"k":[1088],"v":[{"k":[1091],"v":[{"k":[1081],"v":[{"d":{"df":1,"dc":[[0,1]]}}]}]}]}]}]}]}]}]}]},{"d":{"df":1,"dc":[[0,11]]}},{"k":[1085,1090,1087,1089,1073,1092,1076,1075,1096,1095],"v":[{"d":{"df":1,"dc":[[0,1]]},"k":[1080],"v":[{"d":{"df":1,"dc":[[0,1]]}}]},{"k":[1077],"v":[{"k":[1095],"v":[{"k":[1077],"v":[{"k":[1089],"v":[{"k":[1090],"v":[{"k":[1074],"v":[{"k":[1077],"v":[{"k":[1085],"v":[{"k":[1085],"v":[{"k":[1099],"v":[{"k":[1084],"v":[{"d":{"df":1,"dc":[[0,1]]}}]}]}]}]}]}]}]}]}]}]}]},{"k":[1077,1103],"v":[{"k":[1088],"v":[{"k":[1072],"v":[{"k":[1094],"v":[{"k":[1080],"v":[{"k":[1086],"v":[{"k":[1085],"v":[{"k":[1086],"v":[{"k":[1082],"v":[{"k":[46],"v":[{"d":{"df":1,"dc":[[0,1]]}}]}]}]}]}]}]}]}]}]},{"k":[1090],"v":[{"k":[1100],"v":[{"d":{"df":1,"dc":[[0,1]]}}]}]}]},{"k":[1085,1090],"v":[{"k":[1086],"v":[{"k":[1074],"v":[{"k":[1085],"v":[{"k":[1086],"v":[{"k":[1081],"v":[{"d":{"df":1,"dc":[[0,1]]}}]}]}]}]}]},{"k":[1072],"v":[{"k":[1074],"v":[{"k":[1100,1083],"v":[{"d":{"df":1,"dc":[[0,1]]}},{"k":[1103],"v":[{"k":[1081],"v":[{"d":{"df":1,"dc":[[0,1]]}}]}]}]}]}]}]},{"k":[1088,1098],"v":[{"k":[1072],"v":[{"k":[1079],"v":[{"d":{"df":1,"dc":[[0,3]]}}]}]},{"k":[1103],"v":[{"k":[1089],"v":[{"k":[1085],"v":[{"k":[1077],"v":[{"k":[1085],"v":[{"k":[1080],"v":[{"k":[1103],"v":[{"d":{"df":1,"dc":[[0,1]]}}]}]}]}]}]}]}]}]},{"k":[1080],"v":[{"k":[1094],"v":[{"k":[1080],"v":[{"k":[1072],"v":[{"k":[1083],"v":[{"k":[1100],"v":[{"k":[1085],"v":[{"k":[1086,1099],"v":[{"k":[1075],"v":[{"k":[1086],"v":[{"d":{"df":1,"dc":[[0,2]]}}]}]},{"k":[1093],"v":[{"d":{"df":1,"dc":[[0,1]]}}]}]}]}]}]}]}]}]}]},{"k":[1091],"v":[{"k":[1084],"v":[{"k":[1072],"v":[{"k":[1090],"v":[{"k":[1100],"v":[{"k":[1089],"v":[{"k":[1103],"v":[{"k":[46],"v":[{"k":[46],"v":[{"k":[46],"v":[{"d":{"df":1,"dc":[[0,1]]}}]}]}]}]}]}]}]}]}]}]},{"k":[1086],"v":[{"k":[44],"v":[{"d":{"df":1,"dc":[[0,1]]}}]}]},{"k":[1080],"v":[{"k":[1073],"v":[{"k":[1082],"v":[{"k":[1080,1072],"v":[{"k":[58],"v":[{"d":{"df":1,"dc":[[0,1]]}}]},{"d":{"df":1,"dc":[[0,1]]}}]}]}]}]},{"k":[1077],"v":[{"k":[1085],"v":[{"k":[1100],"v":[{"d":{"df":1,"dc":[[0,1]]}}]}]}]}]},{"k":[35],"v":[{"d":{"df":1,"dc":[[0,1]]}}]},{"k":[1077,1084],"v":[{"d":{"df":1,"dc":[[0,1]]},"k":[1083,44],"v":[{"k":[1072],"v":[{"k":[1085],"v":[{"k":[1080],"v":[{"k":[1077],"v":[{"d":{"df":1,"dc":[[0,1]]}}]}]}]}]},{"d":{"df":1,"dc":[[0,1]]}}]},{"k":[1080],"v":[{"d":{"df":1,"dc":[[0,2]]}}]}]},{"k":[1084,1085,1074,1089,1077],"v":[{"k":[1086],"v":[{"k":[1077],"v":[{"k":[44],"v":[{"d":{"df":1,"dc":[[0,1]]}}]}]}]},{"k":[1091],"v":[{"d":{"df":1,"dc":[[0,1]]}}]},{"k":[1086],"v":[{"k":[1086],"v":[{"k":[1073],"v":[{"k":[1097],"v":[{"k":[1077],"v":[{"d":{"df":1,"dc":[[0,1]]}}]}]}]}]}]},{"k":[1082],"v":[{"k":[1088],"v":[{"k":[1080],"v":[{"k":[1085],"v":[{"d":{"df":1,"dc":[[0,1]]}}]}]}]}]},{"k":[1089],"v":[{"k":[1083],"v":[{"k":[1080],"v":[{"d":{"df":1,"dc":[[0,1]]}}]}]}]}]},{"k":[101,118,114],"v":[{"k":[98],"v":[{"k":[105],"v":[{"k":[97],"v":[{"k":[110],"v":[{"k":[44],"v":[{"d":{"df":1,"dc":[[0,1]]}}]}]}]}]}]},{"k":[100],"v":[{"k":[44],"v":[{"d":{"df":1,"dc":[[0,1]]}}]}]},{"k":[105],"v":[{"k":[118],"v":[{"k":[101],"v":[{"k":[115],"v":[{"d":{"df":1,"dc":[[0,1]]}}]}]}]}]}]},{"k":[1086],"v":[{"k":[1081,1078,1084,1075],"v":[{"d":{"df":1,"dc":[[0,1]]}},{"k":[1085],"v":[{"k":[1086],"v":[{"d":{"df":1,"dc":[[0,2]]}}]}]},{"k":[1077],"v":[{"k":[1085],"v":[{"k":[1090],"v":[{"k":[1072],"v":[{"d":{"df":1,"dc":[[0,1]]}}]}]}]}]},{"d":{"df":1,"dc":[[0,1]]},"k":[1091],"v":[{"k":[1090],"v":[{"d":{"df":1,"dc":[[0,1]]}}]}]}]}]},{"k":[97],"v":[{"k":[115],"v":[{"k":[116],"v":[{"k":[114],"v":[{"k":[97],"v":[{"k":[108],"v":[{"k":[105],"v":[{"k":[110],"v":[{"k":[117],"v":[{"k":[120],"v":[{"k":[46],"v":[{"k":[114],"v":[{"k":[117],"v":[{"k":[93],"v":[{"k":[40],"v":[{"k":[104],"v":[{"k":[116],"v":[{"k":[116],"v":[{"k":[112],"v":[{"k":[115],"v":[{"k":[58],"v":[{"k":[47],"v":[{"k":[47],"v":[{"k":[97],"v":[{"k":[115],"v":[{"k":[116],"v":[{"k":[114],"v":[{"k":[97],"v":[{"k":[108],"v":[{"k":[105],"v":[{"k":[110],"v":[{"k":[117],"v":[{"k":[120],"v":[{"k":[46],"v":[{"k":[114],"v":[{"k":[117],"v":[{"k":[47],"v":[{"k":[112],"v":[{"k":[114],"v":[{"k":[111],"v":[{"k":[100],"v":[{"k":[117],"v":[{"k":[99],"v":[{"k":[116],"v":[{"k":[115],"v":[{"k":[47],"v":[{"k":[41],"v":[{"d":{"df":1,"dc":[[0,1]]}}]}]}]}]}]}]}]}]}]}]}]}]}]}]}]}]}]}]}]}]}]}]}]}]}]}]}]}]}]}]}]}]}]}]}]}]}]}]}]}]}]}]}]}]}]}]}]},{"k":[97,1079,1101,1087],"v":[{"k":[115],"v":[{"k":[116],"v":[{"k":[114],"v":[{"k":[97],"v":[{"d":{"df":1,"dc":[[0,1]]}}]}]}]}]},{"k":[1072],"v":[{"k":[1087],"v":[{"k":[1080],"v":[{"k":[1089],"v":[{"k":[1072],"v":[{"k":[1090],"v":[{"k":[1100],"v":[{"d":{"df":1,"dc":[[0,1]]}}]}]}]}]}]}]}]},{"k":[1090],"v":[{"k":[1086],"v":[{"k":[34],"v":[{"k":[44],"v":[{"d":{"df":1,"dc":[[0,1]]}}]}]}]}]},{"k":[1088],"v":[{"k":[1086],"v":[{"k":[1076],"v":[{"k":[1086],"v":[{"k":[1083],"v":[{"k":[1078],"v":[{"k":[1080],"v":[{"k":[1090],"v":[{"k":[1100],"v":[{"k":[34],"v":[{"k":[46],"v":[{"d":{"df":1,"dc":[[0,1]]}}]}]}]}]}]}]}]}]}]}]}]}]},{"k":[111,97],"v":[{"k":[109],"v":[{"k":[109],"v":[{"k":[111],"v":[{"k":[110],"v":[{"d":{"df":1,"dc":[[0,1]]}}]}]}]}]},{"k":[114],"v":[{"k":[100],"v":[{"k":[115],"v":[{"d":{"df":1,"dc":[[0,1]]}}]}]}]}]},{"k":[100],"v":[{"k":[105],"v":[{"k":[116],"v":[{"k":[105],"v":[{"k":[111],"v":[{"k":[110],"v":[{"k":[34],"v":[{"k":[46],"v":[{"d":{"df":1,"dc":[[0,1]]}}]}]}]}]}]}]}]}]},{"k":[1086,1072],"v":[{"k":[1090],"v":[{"k":[1100],"v":[{"d":{"df":1,"dc":[[0,1]]}}]}]},{"k":[1088],"v":[{"k":[1076],"v":[{"k":[1082],"v":[{"k":[1086],"v":[{"k":[1088],"v":[{"k":[46],"v":[{"d":{"df":1,"dc":[[0,1]]}}]}]}]}]}]}]}]},{"k":[97,111],"v":[{"k":[108],"v":[{"k":[101],"v":[{"k":[110],"v":[{"k":[97],"v":[{"k":[101,46],"v":[{"k":[116],"v":[{"k":[99],"v":[{"k":[104],"v":[{"k":[101],"v":[{"k":[114],"v":[{"d":{"df":1,"dc":[[0,5]]},"k":[44],"v":[{"d":{"df":1,"dc":[[0,1]]}}]}]}]}]}]}]},{"k":[105],"v":[{"k":[111],"v":[{"d":{"df":1,"dc":[[0,1]]}}]}]}]}]}]}]}]},{"k":[111],"v":[{"k":[116],"v":[{"d":{"df":1,"dc":[[0,1]]}}]}]}]},{"k":[1080,1072],"v":[{"k":[1085],"v":[{"k":[1076],"v":[{"k":[1086],"v":[{"k":[1074],"v":[{"k":[1089],"v":[{"k":[46],"v":[{"d":{"df":1,"dc":[[0,1]]}}]}]}]}]}]}]},{"k":[1075,1085],"v":[{"k":[1072],"v":[{"k":[1084],"v":[{"k":[58],"v":[{"d":{"df":1,"dc":[[0,1]]}}]}]}]},{"k":[1089],"v":[{"d":{"df":1,"dc":[[0,1]]}}]}]}]},{"k":[108],"v":[{"k":[97],"v":[{"k":[115],"v":[{"k":[104],"v":[{"d":{"df":1,"dc":[[0,1]]},"k":[33],"v":[{"d":{"df":1,"dc":[[0,1]]}}]}]}]}]}]},{"k":[115],"v":[{"d":{"df":1,"dc":[[0,1]]}}]},{"k":[109],"v":[{"k":[97],"v":[{"k":[103],"v":[{"k":[101],"v":[{"k":[115],"v":[{"d":{"df":1,"dc":[[0,1]]}}]}]}]}]}]},{"k":[111],"v":[{"d":{"df":1,"dc":[[0,1]]}}]},{"k":[100],"v":[{"d":{"df":1,"dc":[[0,1]]}}]},{"d":{"df":1,"dc":[[0,1]]}},{"k":[1080],"v":[{"k":[44,46],"v":[{"d":{"df":1,"dc":[[0,1]]}},{"k":[46],"v":[{"k":[46],"v":[{"d":{"df":1,"dc":[[0,1]]}}]}]}]}]},{"k":[46],"v":[{"k":[46],"v":[{"k":[1078],"v":[{"k":[1076],"v":[{"k":[1080],"v":[{"k":[46],"v":[{"k":[46],"v":[{"k":[46],"v":[{"d":{"df":1,"dc":[[0,1]]}}]}]}]}]}]}]}]}]},{"d":{"df":1,"dc":[[0,1]]},"k":[1089],"v":[{"k":[1090],"v":[{"k":[1088],"v":[{"k":[1099],"v":[{"d":{"df":1,"dc":[[0,1]]}}]}]}]}]},{"d":{"df":1,"dc":[[0,1]]}}]}}}}}],"databaseVersion":1.5,"engineVersion":1.5,"filename":"content.db","_persistenceAdapter":null,"_persistenceMethod":null,"_throttledSaves":true}